{
  "lookup": {
    "rules": {
      "[{\"active_loop\": {\"name\": \"movie_recommendation_form\"}, \"prev_action\": {\"action_name\": \"action_listen\"}, \"user\": {\"intent\": \"stop\"}}]": "action_deactivate_loop",
      "[{\"active_loop\": {\"name\": \"movie_recommendation_form\"}, \"prev_action\": {\"action_name\": \"action_listen\"}, \"user\": {\"intent\": \"stop\"}}, {\"active_loop\": {\"name\": \"should_not_be_set\"}, \"prev_action\": {\"action_name\": \"action_deactivate_loop\"}, \"user\": {\"intent\": \"stop\"}}]": "utter_form_stopped",
      "[{\"active_loop\": {\"name\": \"movie_recommendation_form\"}, \"prev_action\": {\"action_name\": \"action_listen\"}, \"user\": {\"intent\": \"stop\"}}, {\"active_loop\": {\"name\": \"should_not_be_set\"}, \"prev_action\": {\"action_name\": \"action_deactivate_loop\"}, \"user\": {\"intent\": \"stop\"}}, {\"active_loop\": {\"name\": \"should_not_be_set\"}, \"prev_action\": {\"action_name\": \"utter_form_stopped\"}, \"user\": {\"intent\": \"stop\"}}]": "action_reset_movie_preferences",
      "[{\"active_loop\": {\"name\": \"movie_recommendation_form\"}, \"prev_action\": {\"action_name\": \"action_listen\"}, \"user\": {\"intent\": \"stop\"}}, {\"active_loop\": {\"name\": \"should_not_be_set\"}, \"prev_action\": {\"action_name\": \"action_deactivate_loop\"}, \"user\": {\"intent\": \"stop\"}}, {\"active_loop\": {\"name\": \"should_not_be_set\"}, \"prev_action\": {\"action_name\": \"utter_form_stopped\"}, \"user\": {\"intent\": \"stop\"}}, {\"active_loop\": {\"name\": \"should_not_be_set\"}, \"prev_action\": {\"action_name\": \"action_reset_movie_preferences\"}, \"user\": {\"intent\": \"stop\"}}]": "action_listen",
      "[{\"active_loop\": {\"name\": \"movie_recommendation_form\"}, \"prev_action\": {\"action_name\": \"action_listen\"}, \"user\": {\"intent\": \"ask_top_movies\"}}]": "utter_no_form_in_form",
      "[{\"active_loop\": {\"name\": \"movie_recommendation_form\"}, \"prev_action\": {\"action_name\": \"action_listen\"}, \"user\": {\"intent\": \"ask_top_movies\"}}, {\"active_loop\": {\"name\": \"movie_recommendation_form\"}, \"prev_action\": {\"action_name\": \"utter_no_form_in_form\"}, \"user\": {\"intent\": \"ask_top_movies\"}}]": "action_resume_form_movie_reccomendation",
      "[{\"active_loop\": {\"name\": \"movie_recommendation_form\"}, \"prev_action\": {\"action_name\": \"action_listen\"}, \"user\": {\"intent\": \"ask_top_movies\"}}, {\"active_loop\": {\"name\": \"movie_recommendation_form\"}, \"prev_action\": {\"action_name\": \"utter_no_form_in_form\"}, \"user\": {\"intent\": \"ask_top_movies\"}}, {\"active_loop\": {\"name\": \"movie_recommendation_form\"}, \"prev_action\": {\"action_name\": \"action_resume_form_movie_reccomendation\"}, \"user\": {\"intent\": \"ask_top_movies\"}}]": "action_listen",
      "[{\"active_loop\": {\"name\": \"movie_recommendation_form\"}, \"prev_action\": {\"action_name\": \"action_listen\"}, \"user\": {\"intent\": \"ask_movies_by_actor\"}}]": "utter_no_form_in_form",
      "[{\"active_loop\": {\"name\": \"movie_recommendation_form\"}, \"prev_action\": {\"action_name\": \"action_listen\"}, \"user\": {\"intent\": \"ask_movies_by_actor\"}}, {\"active_loop\": {\"name\": \"movie_recommendation_form\"}, \"prev_action\": {\"action_name\": \"utter_no_form_in_form\"}, \"user\": {\"intent\": \"ask_movies_by_actor\"}}]": "action_resume_form_movie_reccomendation",
      "[{\"active_loop\": {\"name\": \"movie_recommendation_form\"}, \"prev_action\": {\"action_name\": \"action_listen\"}, \"user\": {\"intent\": \"ask_movies_by_actor\"}}, {\"active_loop\": {\"name\": \"movie_recommendation_form\"}, \"prev_action\": {\"action_name\": \"utter_no_form_in_form\"}, \"user\": {\"intent\": \"ask_movies_by_actor\"}}, {\"active_loop\": {\"name\": \"movie_recommendation_form\"}, \"prev_action\": {\"action_name\": \"action_resume_form_movie_reccomendation\"}, \"user\": {\"intent\": \"ask_movies_by_actor\"}}]": "action_listen",
      "[{\"active_loop\": {\"name\": \"should_not_be_set\"}, \"prev_action\": {\"action_name\": \"film_count_form\"}}]": "action_count_films",
      "[{\"active_loop\": {\"name\": \"should_not_be_set\"}, \"prev_action\": {\"action_name\": \"film_count_form\"}}, {\"active_loop\": {\"name\": \"should_not_be_set\"}, \"prev_action\": {\"action_name\": \"action_count_films\"}}]": "action_listen",
      "[{\"prev_action\": {\"action_name\": \"action_listen\"}, \"user\": {\"intent\": \"stop\"}}]": "action_deactivate_loop",
      "[{\"prev_action\": {\"action_name\": \"action_listen\"}, \"user\": {\"intent\": \"stop\"}}, {\"active_loop\": {\"name\": \"should_not_be_set\"}, \"prev_action\": {\"action_name\": \"action_deactivate_loop\"}, \"user\": {\"intent\": \"stop\"}}]": "utter_form_stopped",
      "[{\"prev_action\": {\"action_name\": \"action_listen\"}, \"user\": {\"intent\": \"stop\"}}, {\"active_loop\": {\"name\": \"should_not_be_set\"}, \"prev_action\": {\"action_name\": \"action_deactivate_loop\"}, \"user\": {\"intent\": \"stop\"}}, {\"active_loop\": {\"name\": \"should_not_be_set\"}, \"prev_action\": {\"action_name\": \"utter_form_stopped\"}, \"user\": {\"intent\": \"stop\"}}]": "action_reset_director_form",
      "[{\"prev_action\": {\"action_name\": \"action_listen\"}, \"user\": {\"intent\": \"stop\"}}, {\"active_loop\": {\"name\": \"should_not_be_set\"}, \"prev_action\": {\"action_name\": \"action_deactivate_loop\"}, \"user\": {\"intent\": \"stop\"}}, {\"active_loop\": {\"name\": \"should_not_be_set\"}, \"prev_action\": {\"action_name\": \"utter_form_stopped\"}, \"user\": {\"intent\": \"stop\"}}, {\"active_loop\": {\"name\": \"should_not_be_set\"}, \"prev_action\": {\"action_name\": \"action_reset_director_form\"}, \"user\": {\"intent\": \"stop\"}}]": "action_listen",
      "[{\"active_loop\": {\"name\": \"movie_recommendation_form\"}, \"prev_action\": {\"action_name\": \"action_listen\"}, \"user\": {\"intent\": \"ask_director\"}}]": "utter_no_form_in_form",
      "[{\"active_loop\": {\"name\": \"movie_recommendation_form\"}, \"prev_action\": {\"action_name\": \"action_listen\"}, \"user\": {\"intent\": \"ask_director\"}}, {\"active_loop\": {\"name\": \"movie_recommendation_form\"}, \"prev_action\": {\"action_name\": \"utter_no_form_in_form\"}, \"user\": {\"intent\": \"ask_director\"}}]": "action_resume_form_movie_reccomendation",
      "[{\"active_loop\": {\"name\": \"movie_recommendation_form\"}, \"prev_action\": {\"action_name\": \"action_listen\"}, \"user\": {\"intent\": \"ask_director\"}}, {\"active_loop\": {\"name\": \"movie_recommendation_form\"}, \"prev_action\": {\"action_name\": \"utter_no_form_in_form\"}, \"user\": {\"intent\": \"ask_director\"}}, {\"active_loop\": {\"name\": \"movie_recommendation_form\"}, \"prev_action\": {\"action_name\": \"action_resume_form_movie_reccomendation\"}, \"user\": {\"intent\": \"ask_director\"}}]": "action_listen",
      "[{\"active_loop\": {\"name\": \"movie_recommendation_form\"}, \"prev_action\": {\"action_name\": \"action_listen\"}, \"user\": {\"intent\": \"ask_film_count\"}}]": "utter_no_form_in_form",
      "[{\"active_loop\": {\"name\": \"movie_recommendation_form\"}, \"prev_action\": {\"action_name\": \"action_listen\"}, \"user\": {\"intent\": \"ask_film_count\"}}, {\"active_loop\": {\"name\": \"movie_recommendation_form\"}, \"prev_action\": {\"action_name\": \"utter_no_form_in_form\"}, \"user\": {\"intent\": \"ask_film_count\"}}]": "action_resume_form_movie_reccomendation",
      "[{\"active_loop\": {\"name\": \"movie_recommendation_form\"}, \"prev_action\": {\"action_name\": \"action_listen\"}, \"user\": {\"intent\": \"ask_film_count\"}}, {\"active_loop\": {\"name\": \"movie_recommendation_form\"}, \"prev_action\": {\"action_name\": \"utter_no_form_in_form\"}, \"user\": {\"intent\": \"ask_film_count\"}}, {\"active_loop\": {\"name\": \"movie_recommendation_form\"}, \"prev_action\": {\"action_name\": \"action_resume_form_movie_reccomendation\"}, \"user\": {\"intent\": \"ask_film_count\"}}]": "action_listen",
      "[{\"active_loop\": {\"name\": \"should_not_be_set\"}, \"prev_action\": {\"action_name\": \"gross_votes_recommendation_form\"}}]": "action_gross_votes_recommendation",
      "[{\"active_loop\": {\"name\": \"should_not_be_set\"}, \"prev_action\": {\"action_name\": \"gross_votes_recommendation_form\"}}, {\"active_loop\": {\"name\": \"should_not_be_set\"}, \"prev_action\": {\"action_name\": \"action_gross_votes_recommendation\"}}]": "action_listen",
      "[{\"prev_action\": {\"action_name\": \"action_listen\"}, \"user\": {\"intent\": \"provide_gross_votes_movie_recommendation\"}}]": "gross_votes_recommendation_form",
      "[{\"prev_action\": {\"action_name\": \"action_listen\"}, \"user\": {\"intent\": \"provide_gross_votes_movie_recommendation\"}}, {\"active_loop\": {\"name\": \"gross_votes_recommendation_form\"}, \"prev_action\": {\"action_name\": \"gross_votes_recommendation_form\"}, \"user\": {\"intent\": \"provide_gross_votes_movie_recommendation\"}}]": "action_listen",
      "[{\"active_loop\": {\"name\": \"movie_recommendation_form\"}, \"prev_action\": {\"action_name\": \"action_listen\"}, \"user\": {\"intent\": \"ask_genre\"}}]": "utter_no_form_in_form",
      "[{\"active_loop\": {\"name\": \"movie_recommendation_form\"}, \"prev_action\": {\"action_name\": \"action_listen\"}, \"user\": {\"intent\": \"ask_genre\"}}, {\"active_loop\": {\"name\": \"movie_recommendation_form\"}, \"prev_action\": {\"action_name\": \"utter_no_form_in_form\"}, \"user\": {\"intent\": \"ask_genre\"}}]": "action_resume_form_movie_reccomendation",
      "[{\"active_loop\": {\"name\": \"movie_recommendation_form\"}, \"prev_action\": {\"action_name\": \"action_listen\"}, \"user\": {\"intent\": \"ask_genre\"}}, {\"active_loop\": {\"name\": \"movie_recommendation_form\"}, \"prev_action\": {\"action_name\": \"utter_no_form_in_form\"}, \"user\": {\"intent\": \"ask_genre\"}}, {\"active_loop\": {\"name\": \"movie_recommendation_form\"}, \"prev_action\": {\"action_name\": \"action_resume_form_movie_reccomendation\"}, \"user\": {\"intent\": \"ask_genre\"}}]": "action_listen",
      "[{\"active_loop\": {\"name\": \"movie_recommendation_form\"}, \"prev_action\": {\"action_name\": \"action_listen\"}, \"user\": {\"intent\": \"start_chat\"}}]": "utter_no_form_in_form",
      "[{\"active_loop\": {\"name\": \"movie_recommendation_form\"}, \"prev_action\": {\"action_name\": \"action_listen\"}, \"user\": {\"intent\": \"start_chat\"}}, {\"active_loop\": {\"name\": \"movie_recommendation_form\"}, \"prev_action\": {\"action_name\": \"utter_no_form_in_form\"}, \"user\": {\"intent\": \"start_chat\"}}]": "action_resume_form_movie_reccomendation",
      "[{\"active_loop\": {\"name\": \"movie_recommendation_form\"}, \"prev_action\": {\"action_name\": \"action_listen\"}, \"user\": {\"intent\": \"start_chat\"}}, {\"active_loop\": {\"name\": \"movie_recommendation_form\"}, \"prev_action\": {\"action_name\": \"utter_no_form_in_form\"}, \"user\": {\"intent\": \"start_chat\"}}, {\"active_loop\": {\"name\": \"movie_recommendation_form\"}, \"prev_action\": {\"action_name\": \"action_resume_form_movie_reccomendation\"}, \"user\": {\"intent\": \"start_chat\"}}]": "action_listen",
      "[{\"active_loop\": {\"name\": \"movie_recommendation_form\"}, \"prev_action\": {\"action_name\": \"action_listen\"}, \"user\": {\"intent\": \"ask_movie_info\"}}]": "utter_no_form_in_form",
      "[{\"active_loop\": {\"name\": \"movie_recommendation_form\"}, \"prev_action\": {\"action_name\": \"action_listen\"}, \"user\": {\"intent\": \"ask_movie_info\"}}, {\"active_loop\": {\"name\": \"movie_recommendation_form\"}, \"prev_action\": {\"action_name\": \"utter_no_form_in_form\"}, \"user\": {\"intent\": \"ask_movie_info\"}}]": "action_resume_form_movie_reccomendation",
      "[{\"active_loop\": {\"name\": \"movie_recommendation_form\"}, \"prev_action\": {\"action_name\": \"action_listen\"}, \"user\": {\"intent\": \"ask_movie_info\"}}, {\"active_loop\": {\"name\": \"movie_recommendation_form\"}, \"prev_action\": {\"action_name\": \"utter_no_form_in_form\"}, \"user\": {\"intent\": \"ask_movie_info\"}}, {\"active_loop\": {\"name\": \"movie_recommendation_form\"}, \"prev_action\": {\"action_name\": \"action_resume_form_movie_reccomendation\"}, \"user\": {\"intent\": \"ask_movie_info\"}}]": "action_listen",
      "[{\"active_loop\": {\"name\": \"movie_recommendation_form\"}, \"prev_action\": {\"action_name\": \"action_listen\"}, \"user\": {\"intent\": \"ask_movies_by_director\"}}]": "utter_no_form_in_form",
      "[{\"active_loop\": {\"name\": \"movie_recommendation_form\"}, \"prev_action\": {\"action_name\": \"action_listen\"}, \"user\": {\"intent\": \"ask_movies_by_director\"}}, {\"active_loop\": {\"name\": \"movie_recommendation_form\"}, \"prev_action\": {\"action_name\": \"utter_no_form_in_form\"}, \"user\": {\"intent\": \"ask_movies_by_director\"}}]": "action_resume_form_movie_reccomendation",
      "[{\"active_loop\": {\"name\": \"movie_recommendation_form\"}, \"prev_action\": {\"action_name\": \"action_listen\"}, \"user\": {\"intent\": \"ask_movies_by_director\"}}, {\"active_loop\": {\"name\": \"movie_recommendation_form\"}, \"prev_action\": {\"action_name\": \"utter_no_form_in_form\"}, \"user\": {\"intent\": \"ask_movies_by_director\"}}, {\"active_loop\": {\"name\": \"movie_recommendation_form\"}, \"prev_action\": {\"action_name\": \"action_resume_form_movie_reccomendation\"}, \"user\": {\"intent\": \"ask_movies_by_director\"}}]": "action_listen",
      "[{\"active_loop\": {\"name\": \"movie_recommendation_form\"}, \"prev_action\": {\"action_name\": \"action_listen\"}, \"user\": {\"intent\": \"ask_capabilities\"}}]": "utter_no_form_in_form",
      "[{\"active_loop\": {\"name\": \"movie_recommendation_form\"}, \"prev_action\": {\"action_name\": \"action_listen\"}, \"user\": {\"intent\": \"ask_capabilities\"}}, {\"active_loop\": {\"name\": \"movie_recommendation_form\"}, \"prev_action\": {\"action_name\": \"utter_no_form_in_form\"}, \"user\": {\"intent\": \"ask_capabilities\"}}]": "action_resume_form_movie_reccomendation",
      "[{\"active_loop\": {\"name\": \"movie_recommendation_form\"}, \"prev_action\": {\"action_name\": \"action_listen\"}, \"user\": {\"intent\": \"ask_capabilities\"}}, {\"active_loop\": {\"name\": \"movie_recommendation_form\"}, \"prev_action\": {\"action_name\": \"utter_no_form_in_form\"}, \"user\": {\"intent\": \"ask_capabilities\"}}, {\"active_loop\": {\"name\": \"movie_recommendation_form\"}, \"prev_action\": {\"action_name\": \"action_resume_form_movie_reccomendation\"}, \"user\": {\"intent\": \"ask_capabilities\"}}]": "action_listen",
      "[{\"prev_action\": {\"action_name\": \"action_listen\"}, \"user\": {\"intent\": \"provide_movie_recommendation\"}}]": "movie_recommendation_form",
      "[{\"prev_action\": {\"action_name\": \"action_listen\"}, \"user\": {\"intent\": \"provide_movie_recommendation\"}}, {\"active_loop\": {\"name\": \"movie_recommendation_form\"}, \"prev_action\": {\"action_name\": \"movie_recommendation_form\"}, \"user\": {\"intent\": \"provide_movie_recommendation\"}}]": "action_listen",
      "[{\"prev_action\": {\"action_name\": \"action_listen\"}, \"user\": {\"intent\": \"ask_film_count\"}}]": "film_count_form",
      "[{\"prev_action\": {\"action_name\": \"action_listen\"}, \"user\": {\"intent\": \"ask_film_count\"}}, {\"active_loop\": {\"name\": \"film_count_form\"}, \"prev_action\": {\"action_name\": \"film_count_form\"}, \"user\": {\"intent\": \"ask_film_count\"}}]": "action_listen",
      "[{\"active_loop\": {\"name\": \"should_not_be_set\"}, \"prev_action\": {\"action_name\": \"action_listen\"}, \"user\": {\"intent\": \"out_of_scope\"}}]": "utter_out_of_scope",
      "[{\"active_loop\": {\"name\": \"should_not_be_set\"}, \"prev_action\": {\"action_name\": \"action_listen\"}, \"user\": {\"intent\": \"out_of_scope\"}}, {\"active_loop\": {\"name\": \"should_not_be_set\"}, \"prev_action\": {\"action_name\": \"utter_out_of_scope\"}, \"user\": {\"intent\": \"out_of_scope\"}}]": "action_listen",
      "[{\"active_loop\": {\"name\": \"gross_votes_recommendation_form\"}, \"prev_action\": {\"action_name\": \"action_listen\"}, \"user\": {\"intent\": \"stop\"}}]": "action_deactivate_loop",
      "[{\"active_loop\": {\"name\": \"gross_votes_recommendation_form\"}, \"prev_action\": {\"action_name\": \"action_listen\"}, \"user\": {\"intent\": \"stop\"}}, {\"active_loop\": {\"name\": \"should_not_be_set\"}, \"prev_action\": {\"action_name\": \"action_deactivate_loop\"}, \"user\": {\"intent\": \"stop\"}}]": "utter_form_stopped",
      "[{\"active_loop\": {\"name\": \"gross_votes_recommendation_form\"}, \"prev_action\": {\"action_name\": \"action_listen\"}, \"user\": {\"intent\": \"stop\"}}, {\"active_loop\": {\"name\": \"should_not_be_set\"}, \"prev_action\": {\"action_name\": \"action_deactivate_loop\"}, \"user\": {\"intent\": \"stop\"}}, {\"active_loop\": {\"name\": \"should_not_be_set\"}, \"prev_action\": {\"action_name\": \"utter_form_stopped\"}, \"user\": {\"intent\": \"stop\"}}]": "action_reset_gross_votes_recommendation_form",
      "[{\"active_loop\": {\"name\": \"gross_votes_recommendation_form\"}, \"prev_action\": {\"action_name\": \"action_listen\"}, \"user\": {\"intent\": \"stop\"}}, {\"active_loop\": {\"name\": \"should_not_be_set\"}, \"prev_action\": {\"action_name\": \"action_deactivate_loop\"}, \"user\": {\"intent\": \"stop\"}}, {\"active_loop\": {\"name\": \"should_not_be_set\"}, \"prev_action\": {\"action_name\": \"utter_form_stopped\"}, \"user\": {\"intent\": \"stop\"}}, {\"active_loop\": {\"name\": \"should_not_be_set\"}, \"prev_action\": {\"action_name\": \"action_reset_gross_votes_recommendation_form\"}, \"user\": {\"intent\": \"stop\"}}]": "action_listen",
      "[{\"active_loop\": {\"name\": \"should_not_be_set\"}, \"prev_action\": {\"action_name\": \"movie_recommendation_form\"}}]": "action_provide_movie_recommendation",
      "[{\"active_loop\": {\"name\": \"should_not_be_set\"}, \"prev_action\": {\"action_name\": \"movie_recommendation_form\"}}, {\"active_loop\": {\"name\": \"should_not_be_set\"}, \"prev_action\": {\"action_name\": \"action_provide_movie_recommendation\"}}]": "action_listen"
    },
    "rule_only_slots": [],
    "rule_only_loops": [
      "movie_recommendation_form",
      "gross_votes_recommendation_form",
      "film_count_form"
    ],
    "rules_for_loop_unhappy_path": {
      "[{\"prev_action\": {\"action_name\": \"action_listen\"}}, {\"active_loop\": {\"name\": \"movie_recommendation_form\"}, \"prev_action\": {\"action_name\": \"utter_no_form_in_form\"}, \"user\": {\"intent\": \"ask_top_movies\"}}]": "do_not_predict_loop_action",
      "[{\"prev_action\": {\"action_name\": \"utter_no_form_in_form\"}}, {\"active_loop\": {\"name\": \"movie_recommendation_form\"}, \"prev_action\": {\"action_name\": \"action_resume_form_movie_reccomendation\"}, \"user\": {\"intent\": \"ask_top_movies\"}}]": "do_not_predict_loop_action",
      "[{\"prev_action\": {\"action_name\": \"action_listen\"}}, {\"active_loop\": {\"name\": \"movie_recommendation_form\"}, \"prev_action\": {\"action_name\": \"utter_no_form_in_form\"}, \"user\": {\"intent\": \"ask_movies_by_actor\"}}]": "do_not_predict_loop_action",
      "[{\"prev_action\": {\"action_name\": \"utter_no_form_in_form\"}}, {\"active_loop\": {\"name\": \"movie_recommendation_form\"}, \"prev_action\": {\"action_name\": \"action_resume_form_movie_reccomendation\"}, \"user\": {\"intent\": \"ask_movies_by_actor\"}}]": "do_not_predict_loop_action",
      "[{\"prev_action\": {\"action_name\": \"action_listen\"}}, {\"active_loop\": {\"name\": \"movie_recommendation_form\"}, \"prev_action\": {\"action_name\": \"utter_no_form_in_form\"}, \"user\": {\"intent\": \"ask_director\"}}]": "do_not_predict_loop_action",
      "[{\"prev_action\": {\"action_name\": \"utter_no_form_in_form\"}}, {\"active_loop\": {\"name\": \"movie_recommendation_form\"}, \"prev_action\": {\"action_name\": \"action_resume_form_movie_reccomendation\"}, \"user\": {\"intent\": \"ask_director\"}}]": "do_not_predict_loop_action",
      "[{\"prev_action\": {\"action_name\": \"action_listen\"}}, {\"active_loop\": {\"name\": \"movie_recommendation_form\"}, \"prev_action\": {\"action_name\": \"utter_no_form_in_form\"}, \"user\": {\"intent\": \"ask_film_count\"}}]": "do_not_predict_loop_action",
      "[{\"prev_action\": {\"action_name\": \"utter_no_form_in_form\"}}, {\"active_loop\": {\"name\": \"movie_recommendation_form\"}, \"prev_action\": {\"action_name\": \"action_resume_form_movie_reccomendation\"}, \"user\": {\"intent\": \"ask_film_count\"}}]": "do_not_predict_loop_action",
      "[{\"prev_action\": {\"action_name\": \"action_listen\"}}, {\"active_loop\": {\"name\": \"gross_votes_recommendation_form\"}, \"prev_action\": {\"action_name\": \"gross_votes_recommendation_form\"}, \"user\": {\"intent\": \"provide_gross_votes_movie_recommendation\"}}]": "do_not_predict_loop_action",
      "[{\"prev_action\": {\"action_name\": \"action_listen\"}}, {\"active_loop\": {\"name\": \"movie_recommendation_form\"}, \"prev_action\": {\"action_name\": \"utter_no_form_in_form\"}, \"user\": {\"intent\": \"ask_genre\"}}]": "do_not_predict_loop_action",
      "[{\"prev_action\": {\"action_name\": \"utter_no_form_in_form\"}}, {\"active_loop\": {\"name\": \"movie_recommendation_form\"}, \"prev_action\": {\"action_name\": \"action_resume_form_movie_reccomendation\"}, \"user\": {\"intent\": \"ask_genre\"}}]": "do_not_predict_loop_action",
      "[{\"prev_action\": {\"action_name\": \"action_listen\"}}, {\"active_loop\": {\"name\": \"movie_recommendation_form\"}, \"prev_action\": {\"action_name\": \"utter_no_form_in_form\"}, \"user\": {\"intent\": \"start_chat\"}}]": "do_not_predict_loop_action",
      "[{\"prev_action\": {\"action_name\": \"utter_no_form_in_form\"}}, {\"active_loop\": {\"name\": \"movie_recommendation_form\"}, \"prev_action\": {\"action_name\": \"action_resume_form_movie_reccomendation\"}, \"user\": {\"intent\": \"start_chat\"}}]": "do_not_predict_loop_action",
      "[{\"prev_action\": {\"action_name\": \"action_listen\"}}, {\"active_loop\": {\"name\": \"movie_recommendation_form\"}, \"prev_action\": {\"action_name\": \"utter_no_form_in_form\"}, \"user\": {\"intent\": \"ask_movie_info\"}}]": "do_not_predict_loop_action",
      "[{\"prev_action\": {\"action_name\": \"utter_no_form_in_form\"}}, {\"active_loop\": {\"name\": \"movie_recommendation_form\"}, \"prev_action\": {\"action_name\": \"action_resume_form_movie_reccomendation\"}, \"user\": {\"intent\": \"ask_movie_info\"}}]": "do_not_predict_loop_action",
      "[{\"prev_action\": {\"action_name\": \"action_listen\"}}, {\"active_loop\": {\"name\": \"movie_recommendation_form\"}, \"prev_action\": {\"action_name\": \"utter_no_form_in_form\"}, \"user\": {\"intent\": \"ask_movies_by_director\"}}]": "do_not_predict_loop_action",
      "[{\"prev_action\": {\"action_name\": \"utter_no_form_in_form\"}}, {\"active_loop\": {\"name\": \"movie_recommendation_form\"}, \"prev_action\": {\"action_name\": \"action_resume_form_movie_reccomendation\"}, \"user\": {\"intent\": \"ask_movies_by_director\"}}]": "do_not_predict_loop_action",
      "[{\"prev_action\": {\"action_name\": \"action_listen\"}}, {\"active_loop\": {\"name\": \"movie_recommendation_form\"}, \"prev_action\": {\"action_name\": \"utter_no_form_in_form\"}, \"user\": {\"intent\": \"ask_capabilities\"}}]": "do_not_predict_loop_action",
      "[{\"prev_action\": {\"action_name\": \"utter_no_form_in_form\"}}, {\"active_loop\": {\"name\": \"movie_recommendation_form\"}, \"prev_action\": {\"action_name\": \"action_resume_form_movie_reccomendation\"}, \"user\": {\"intent\": \"ask_capabilities\"}}]": "do_not_predict_loop_action",
      "[{\"prev_action\": {\"action_name\": \"action_listen\"}}, {\"active_loop\": {\"name\": \"movie_recommendation_form\"}, \"prev_action\": {\"action_name\": \"movie_recommendation_form\"}, \"user\": {\"intent\": \"provide_movie_recommendation\"}}]": "do_not_predict_loop_action",
      "[{\"prev_action\": {\"action_name\": \"action_listen\"}}, {\"active_loop\": {\"name\": \"film_count_form\"}, \"prev_action\": {\"action_name\": \"film_count_form\"}, \"user\": {\"intent\": \"ask_film_count\"}}]": "do_not_predict_loop_action"
    },
    "rules_not_in_stories": [
      "handling active loops and forms - gross_votes_recommendation_form",
      "[{\"active_loop\": {\"name\": \"movie_recommendation_form\"}, \"prev_action\": {\"action_name\": \"action_listen\"}, \"user\": {\"intent\": \"ask_film_count\"}}]",
      "predicting default action with intent restart",
      "[{\"active_loop\": {\"name\": \"movie_recommendation_form\"}, \"prev_action\": {\"action_name\": \"action_listen\"}, \"user\": {\"intent\": \"ask_movies_by_director\"}}, {\"active_loop\": {\"name\": \"movie_recommendation_form\"}, \"prev_action\": {\"action_name\": \"utter_no_form_in_form\"}, \"user\": {\"intent\": \"ask_movies_by_director\"}}, {\"active_loop\": {\"name\": \"movie_recommendation_form\"}, \"prev_action\": {\"action_name\": \"action_resume_form_movie_reccomendation\"}, \"user\": {\"intent\": \"ask_movies_by_director\"}}]",
      "[{\"active_loop\": {\"name\": \"movie_recommendation_form\"}, \"prev_action\": {\"action_name\": \"action_listen\"}, \"user\": {\"intent\": \"start_chat\"}}, {\"active_loop\": {\"name\": \"movie_recommendation_form\"}, \"prev_action\": {\"action_name\": \"utter_no_form_in_form\"}, \"user\": {\"intent\": \"start_chat\"}}]",
      "[{\"active_loop\": {\"name\": \"movie_recommendation_form\"}, \"prev_action\": {\"action_name\": \"action_listen\"}, \"user\": {\"intent\": \"ask_movies_by_actor\"}}, {\"active_loop\": {\"name\": \"movie_recommendation_form\"}, \"prev_action\": {\"action_name\": \"utter_no_form_in_form\"}, \"user\": {\"intent\": \"ask_movies_by_actor\"}}]",
      "[{\"active_loop\": {\"name\": \"movie_recommendation_form\"}, \"prev_action\": {\"action_name\": \"action_listen\"}, \"user\": {\"intent\": \"ask_movie_info\"}}, {\"active_loop\": {\"name\": \"movie_recommendation_form\"}, \"prev_action\": {\"action_name\": \"utter_no_form_in_form\"}, \"user\": {\"intent\": \"ask_movie_info\"}}]",
      "[{\"active_loop\": {\"name\": \"movie_recommendation_form\"}, \"prev_action\": {\"action_name\": \"action_listen\"}, \"user\": {\"intent\": \"ask_top_movies\"}}, {\"active_loop\": {\"name\": \"movie_recommendation_form\"}, \"prev_action\": {\"action_name\": \"utter_no_form_in_form\"}, \"user\": {\"intent\": \"ask_top_movies\"}}, {\"active_loop\": {\"name\": \"movie_recommendation_form\"}, \"prev_action\": {\"action_name\": \"action_resume_form_movie_reccomendation\"}, \"user\": {\"intent\": \"ask_top_movies\"}}]",
      "[{\"active_loop\": {\"name\": \"movie_recommendation_form\"}, \"prev_action\": {\"action_name\": \"action_listen\"}, \"user\": {\"intent\": \"ask_director\"}}]",
      "handling active loops and forms - movie_recommendation_form - action_listen",
      "[{\"active_loop\": {\"name\": \"movie_recommendation_form\"}, \"prev_action\": {\"action_name\": \"action_listen\"}, \"user\": {\"intent\": \"ask_top_movies\"}}]",
      "[{\"active_loop\": {\"name\": \"should_not_be_set\"}, \"prev_action\": {\"action_name\": \"action_listen\"}, \"user\": {\"intent\": \"out_of_scope\"}}]",
      "[{\"prev_action\": {\"action_name\": \"action_listen\"}, \"user\": {\"intent\": \"stop\"}}, {\"active_loop\": {\"name\": \"should_not_be_set\"}, \"prev_action\": {\"action_name\": \"action_deactivate_loop\"}, \"user\": {\"intent\": \"stop\"}}, {\"active_loop\": {\"name\": \"should_not_be_set\"}, \"prev_action\": {\"action_name\": \"utter_form_stopped\"}, \"user\": {\"intent\": \"stop\"}}]",
      "[{\"active_loop\": {\"name\": \"movie_recommendation_form\"}, \"prev_action\": {\"action_name\": \"action_listen\"}, \"user\": {\"intent\": \"ask_director\"}}, {\"active_loop\": {\"name\": \"movie_recommendation_form\"}, \"prev_action\": {\"action_name\": \"utter_no_form_in_form\"}, \"user\": {\"intent\": \"ask_director\"}}]",
      "[{\"prev_action\": {\"action_name\": \"action_listen\"}, \"user\": {\"intent\": \"stop\"}}, {\"active_loop\": {\"name\": \"should_not_be_set\"}, \"prev_action\": {\"action_name\": \"action_deactivate_loop\"}, \"user\": {\"intent\": \"stop\"}}]",
      "[{\"active_loop\": {\"name\": \"should_not_be_set\"}, \"prev_action\": {\"action_name\": \"gross_votes_recommendation_form\"}}, {\"active_loop\": {\"name\": \"should_not_be_set\"}, \"prev_action\": {\"action_name\": \"action_gross_votes_recommendation\"}}]",
      "[{\"active_loop\": {\"name\": \"movie_recommendation_form\"}, \"prev_action\": {\"action_name\": \"action_listen\"}, \"user\": {\"intent\": \"ask_top_movies\"}}, {\"active_loop\": {\"name\": \"movie_recommendation_form\"}, \"prev_action\": {\"action_name\": \"utter_no_form_in_form\"}, \"user\": {\"intent\": \"ask_top_movies\"}}]",
      "[{\"active_loop\": {\"name\": \"movie_recommendation_form\"}, \"prev_action\": {\"action_name\": \"action_listen\"}, \"user\": {\"intent\": \"ask_genre\"}}, {\"active_loop\": {\"name\": \"movie_recommendation_form\"}, \"prev_action\": {\"action_name\": \"utter_no_form_in_form\"}, \"user\": {\"intent\": \"ask_genre\"}}, {\"active_loop\": {\"name\": \"movie_recommendation_form\"}, \"prev_action\": {\"action_name\": \"action_resume_form_movie_reccomendation\"}, \"user\": {\"intent\": \"ask_genre\"}}]",
      "[{\"active_loop\": {\"name\": \"movie_recommendation_form\"}, \"prev_action\": {\"action_name\": \"action_listen\"}, \"user\": {\"intent\": \"ask_movie_info\"}}, {\"active_loop\": {\"name\": \"movie_recommendation_form\"}, \"prev_action\": {\"action_name\": \"utter_no_form_in_form\"}, \"user\": {\"intent\": \"ask_movie_info\"}}, {\"active_loop\": {\"name\": \"movie_recommendation_form\"}, \"prev_action\": {\"action_name\": \"action_resume_form_movie_reccomendation\"}, \"user\": {\"intent\": \"ask_movie_info\"}}]",
      "[{\"active_loop\": {\"name\": \"movie_recommendation_form\"}, \"prev_action\": {\"action_name\": \"action_listen\"}, \"user\": {\"intent\": \"start_chat\"}}]",
      "[{\"active_loop\": {\"name\": \"movie_recommendation_form\"}, \"prev_action\": {\"action_name\": \"action_listen\"}, \"user\": {\"intent\": \"ask_movies_by_director\"}}]",
      "[{\"active_loop\": {\"name\": \"should_not_be_set\"}, \"prev_action\": {\"action_name\": \"action_listen\"}, \"user\": {\"intent\": \"out_of_scope\"}}, {\"active_loop\": {\"name\": \"should_not_be_set\"}, \"prev_action\": {\"action_name\": \"utter_out_of_scope\"}, \"user\": {\"intent\": \"out_of_scope\"}}]",
      "handling active loops and forms - film_count_form - action_listen",
      "[{\"active_loop\": {\"name\": \"should_not_be_set\"}, \"prev_action\": {\"action_name\": \"movie_recommendation_form\"}}]",
      "[{\"active_loop\": {\"name\": \"gross_votes_recommendation_form\"}, \"prev_action\": {\"action_name\": \"action_listen\"}, \"user\": {\"intent\": \"stop\"}}]",
      "[{\"active_loop\": {\"name\": \"movie_recommendation_form\"}, \"prev_action\": {\"action_name\": \"action_listen\"}, \"user\": {\"intent\": \"ask_capabilities\"}}]",
      "[{\"active_loop\": {\"name\": \"movie_recommendation_form\"}, \"prev_action\": {\"action_name\": \"action_listen\"}, \"user\": {\"intent\": \"stop\"}}]",
      "[{\"active_loop\": {\"name\": \"movie_recommendation_form\"}, \"prev_action\": {\"action_name\": \"action_listen\"}, \"user\": {\"intent\": \"ask_genre\"}}]",
      "[{\"prev_action\": {\"action_name\": \"action_listen\"}, \"user\": {\"intent\": \"stop\"}}]",
      "[{\"prev_action\": {\"action_name\": \"action_listen\"}, \"user\": {\"intent\": \"provide_movie_recommendation\"}}]",
      "[{\"active_loop\": {\"name\": \"movie_recommendation_form\"}, \"prev_action\": {\"action_name\": \"action_listen\"}, \"user\": {\"intent\": \"ask_movie_info\"}}]",
      "[{\"active_loop\": {\"name\": \"movie_recommendation_form\"}, \"prev_action\": {\"action_name\": \"action_listen\"}, \"user\": {\"intent\": \"ask_director\"}}, {\"active_loop\": {\"name\": \"movie_recommendation_form\"}, \"prev_action\": {\"action_name\": \"utter_no_form_in_form\"}, \"user\": {\"intent\": \"ask_director\"}}, {\"active_loop\": {\"name\": \"movie_recommendation_form\"}, \"prev_action\": {\"action_name\": \"action_resume_form_movie_reccomendation\"}, \"user\": {\"intent\": \"ask_director\"}}]",
      "[{\"active_loop\": {\"name\": \"should_not_be_set\"}, \"prev_action\": {\"action_name\": \"film_count_form\"}}, {\"active_loop\": {\"name\": \"should_not_be_set\"}, \"prev_action\": {\"action_name\": \"action_count_films\"}}]",
      "[{\"active_loop\": {\"name\": \"movie_recommendation_form\"}, \"prev_action\": {\"action_name\": \"action_listen\"}, \"user\": {\"intent\": \"ask_genre\"}}, {\"active_loop\": {\"name\": \"movie_recommendation_form\"}, \"prev_action\": {\"action_name\": \"utter_no_form_in_form\"}, \"user\": {\"intent\": \"ask_genre\"}}]",
      "predicting default action with intent back",
      "[{\"active_loop\": {\"name\": \"movie_recommendation_form\"}, \"prev_action\": {\"action_name\": \"action_listen\"}, \"user\": {\"intent\": \"stop\"}}, {\"active_loop\": {\"name\": \"should_not_be_set\"}, \"prev_action\": {\"action_name\": \"action_deactivate_loop\"}, \"user\": {\"intent\": \"stop\"}}, {\"active_loop\": {\"name\": \"should_not_be_set\"}, \"prev_action\": {\"action_name\": \"utter_form_stopped\"}, \"user\": {\"intent\": \"stop\"}}, {\"active_loop\": {\"name\": \"should_not_be_set\"}, \"prev_action\": {\"action_name\": \"action_reset_movie_preferences\"}, \"user\": {\"intent\": \"stop\"}}]",
      "[{\"active_loop\": {\"name\": \"movie_recommendation_form\"}, \"prev_action\": {\"action_name\": \"action_listen\"}, \"user\": {\"intent\": \"ask_movies_by_actor\"}}, {\"active_loop\": {\"name\": \"movie_recommendation_form\"}, \"prev_action\": {\"action_name\": \"utter_no_form_in_form\"}, \"user\": {\"intent\": \"ask_movies_by_actor\"}}, {\"active_loop\": {\"name\": \"movie_recommendation_form\"}, \"prev_action\": {\"action_name\": \"action_resume_form_movie_reccomendation\"}, \"user\": {\"intent\": \"ask_movies_by_actor\"}}]",
      "[{\"prev_action\": {\"action_name\": \"action_listen\"}, \"user\": {\"intent\": \"ask_film_count\"}}]",
      "[{\"active_loop\": {\"name\": \"movie_recommendation_form\"}, \"prev_action\": {\"action_name\": \"action_listen\"}, \"user\": {\"intent\": \"ask_film_count\"}}, {\"active_loop\": {\"name\": \"movie_recommendation_form\"}, \"prev_action\": {\"action_name\": \"utter_no_form_in_form\"}, \"user\": {\"intent\": \"ask_film_count\"}}]",
      "[{\"active_loop\": {\"name\": \"movie_recommendation_form\"}, \"prev_action\": {\"action_name\": \"action_listen\"}, \"user\": {\"intent\": \"ask_movies_by_actor\"}}]",
      "[{\"active_loop\": {\"name\": \"movie_recommendation_form\"}, \"prev_action\": {\"action_name\": \"action_listen\"}, \"user\": {\"intent\": \"stop\"}}, {\"active_loop\": {\"name\": \"should_not_be_set\"}, \"prev_action\": {\"action_name\": \"action_deactivate_loop\"}, \"user\": {\"intent\": \"stop\"}}]",
      "[{\"active_loop\": {\"name\": \"gross_votes_recommendation_form\"}, \"prev_action\": {\"action_name\": \"action_listen\"}, \"user\": {\"intent\": \"stop\"}}, {\"active_loop\": {\"name\": \"should_not_be_set\"}, \"prev_action\": {\"action_name\": \"action_deactivate_loop\"}, \"user\": {\"intent\": \"stop\"}}, {\"active_loop\": {\"name\": \"should_not_be_set\"}, \"prev_action\": {\"action_name\": \"utter_form_stopped\"}, \"user\": {\"intent\": \"stop\"}}]",
      "[{\"active_loop\": {\"name\": \"movie_recommendation_form\"}, \"prev_action\": {\"action_name\": \"action_listen\"}, \"user\": {\"intent\": \"start_chat\"}}, {\"active_loop\": {\"name\": \"movie_recommendation_form\"}, \"prev_action\": {\"action_name\": \"utter_no_form_in_form\"}, \"user\": {\"intent\": \"start_chat\"}}, {\"active_loop\": {\"name\": \"movie_recommendation_form\"}, \"prev_action\": {\"action_name\": \"action_resume_form_movie_reccomendation\"}, \"user\": {\"intent\": \"start_chat\"}}]",
      "[{\"active_loop\": {\"name\": \"gross_votes_recommendation_form\"}, \"prev_action\": {\"action_name\": \"action_listen\"}, \"user\": {\"intent\": \"stop\"}}, {\"active_loop\": {\"name\": \"should_not_be_set\"}, \"prev_action\": {\"action_name\": \"action_deactivate_loop\"}, \"user\": {\"intent\": \"stop\"}}, {\"active_loop\": {\"name\": \"should_not_be_set\"}, \"prev_action\": {\"action_name\": \"utter_form_stopped\"}, \"user\": {\"intent\": \"stop\"}}, {\"active_loop\": {\"name\": \"should_not_be_set\"}, \"prev_action\": {\"action_name\": \"action_reset_gross_votes_recommendation_form\"}, \"user\": {\"intent\": \"stop\"}}]",
      "[{\"active_loop\": {\"name\": \"should_not_be_set\"}, \"prev_action\": {\"action_name\": \"movie_recommendation_form\"}}, {\"active_loop\": {\"name\": \"should_not_be_set\"}, \"prev_action\": {\"action_name\": \"action_provide_movie_recommendation\"}}]",
      "handling active loops and forms - movie_recommendation_form",
      "[{\"active_loop\": {\"name\": \"movie_recommendation_form\"}, \"prev_action\": {\"action_name\": \"action_listen\"}, \"user\": {\"intent\": \"ask_film_count\"}}, {\"active_loop\": {\"name\": \"movie_recommendation_form\"}, \"prev_action\": {\"action_name\": \"utter_no_form_in_form\"}, \"user\": {\"intent\": \"ask_film_count\"}}, {\"active_loop\": {\"name\": \"movie_recommendation_form\"}, \"prev_action\": {\"action_name\": \"action_resume_form_movie_reccomendation\"}, \"user\": {\"intent\": \"ask_film_count\"}}]",
      "[{\"active_loop\": {\"name\": \"should_not_be_set\"}, \"prev_action\": {\"action_name\": \"gross_votes_recommendation_form\"}}]",
      "[{\"prev_action\": {\"action_name\": \"action_listen\"}, \"user\": {\"intent\": \"provide_gross_votes_movie_recommendation\"}}]",
      "handling active loops and forms - film_count_form",
      "[{\"active_loop\": {\"name\": \"gross_votes_recommendation_form\"}, \"prev_action\": {\"action_name\": \"action_listen\"}, \"user\": {\"intent\": \"stop\"}}, {\"active_loop\": {\"name\": \"should_not_be_set\"}, \"prev_action\": {\"action_name\": \"action_deactivate_loop\"}, \"user\": {\"intent\": \"stop\"}}]",
      "[{\"active_loop\": {\"name\": \"should_not_be_set\"}, \"prev_action\": {\"action_name\": \"film_count_form\"}}]",
      "[{\"active_loop\": {\"name\": \"movie_recommendation_form\"}, \"prev_action\": {\"action_name\": \"action_listen\"}, \"user\": {\"intent\": \"ask_capabilities\"}}, {\"active_loop\": {\"name\": \"movie_recommendation_form\"}, \"prev_action\": {\"action_name\": \"utter_no_form_in_form\"}, \"user\": {\"intent\": \"ask_capabilities\"}}]",
      "[{\"prev_action\": {\"action_name\": \"action_listen\"}, \"user\": {\"intent\": \"stop\"}}, {\"active_loop\": {\"name\": \"should_not_be_set\"}, \"prev_action\": {\"action_name\": \"action_deactivate_loop\"}, \"user\": {\"intent\": \"stop\"}}, {\"active_loop\": {\"name\": \"should_not_be_set\"}, \"prev_action\": {\"action_name\": \"utter_form_stopped\"}, \"user\": {\"intent\": \"stop\"}}, {\"active_loop\": {\"name\": \"should_not_be_set\"}, \"prev_action\": {\"action_name\": \"action_reset_director_form\"}, \"user\": {\"intent\": \"stop\"}}]",
      "handling active loops and forms - gross_votes_recommendation_form - action_listen",
      "[{\"active_loop\": {\"name\": \"movie_recommendation_form\"}, \"prev_action\": {\"action_name\": \"action_listen\"}, \"user\": {\"intent\": \"ask_movies_by_director\"}}, {\"active_loop\": {\"name\": \"movie_recommendation_form\"}, \"prev_action\": {\"action_name\": \"utter_no_form_in_form\"}, \"user\": {\"intent\": \"ask_movies_by_director\"}}]",
      "[{\"active_loop\": {\"name\": \"movie_recommendation_form\"}, \"prev_action\": {\"action_name\": \"action_listen\"}, \"user\": {\"intent\": \"stop\"}}, {\"active_loop\": {\"name\": \"should_not_be_set\"}, \"prev_action\": {\"action_name\": \"action_deactivate_loop\"}, \"user\": {\"intent\": \"stop\"}}, {\"active_loop\": {\"name\": \"should_not_be_set\"}, \"prev_action\": {\"action_name\": \"utter_form_stopped\"}, \"user\": {\"intent\": \"stop\"}}]",
      "predicting default action with intent session_start",
      "[{\"active_loop\": {\"name\": \"movie_recommendation_form\"}, \"prev_action\": {\"action_name\": \"action_listen\"}, \"user\": {\"intent\": \"ask_capabilities\"}}, {\"active_loop\": {\"name\": \"movie_recommendation_form\"}, \"prev_action\": {\"action_name\": \"utter_no_form_in_form\"}, \"user\": {\"intent\": \"ask_capabilities\"}}, {\"active_loop\": {\"name\": \"movie_recommendation_form\"}, \"prev_action\": {\"action_name\": \"action_resume_form_movie_reccomendation\"}, \"user\": {\"intent\": \"ask_capabilities\"}}]"
    ]
  }
}